{
  "description": {
    "en": "Preceptor \u015ar\u012b Chandra\u015bekharendra having remained in the P\u012b\u1e6dha for thirty-seven years attained Siddhi on K\u1e5b\u1e63\u1e47advit\u012bya of Pu\u1e63ya month in the year Subhak\u1e5bt. \u015ar\u012b Ma\u1e6dha moved to Kumbhaghona town during the period of this \u0101c\u0101rya; his siddhi was also in Kumbhaghona. \u015aiv\u0101\u1e63\u1e6dapad\u012b, a lyrical work on the model of Gitagovinda of \u015ar\u012b Jayadeva was composed only by this \u0101c\u0101rya. His siddhi was during \u015aalivahana era 1705."
  },
  "id": "kAJcI 62 jagadguru zrI~candrazEkharEndra sarasvatI 5 ArAdhanA",
  "image": "kanchi-jagadgurus/jagadguru-62.jpg",
  "jsonClass": "HinduCalendarEvent",
  "priority": "paraviddha",
  "references_primary": [
    "Punya Shloka Manjari"
  ],
  "references_secondary": [
    "www.kamakoti.org"
  ],
  "shlokas": [
    "saMyatsu viklavE lOkE pITham ArUDhavAn mahAn.\nitihAsagarbhagUDhanAmadhAmAdipUrvakaH..8..\nanAma sarvanAmaitad brahmEtIva pradarzayan.\njayatyabhayadazcandrazEkharEndrO yatIzvaraH..9..\nzrImaThaM kumbhaghONaM yO'nayannayavid AtmavAn.\ntatraiva saMsthitO yatra maThO'bdadvizatIM sthitaH..10..\nzrIcandrazEkharEndraH saptatriMzatsamAH sthitaH pIThE.\nzubhakRti puSyE kRSNadvitIyatithyAm iyAya kaivalyam..11..\n\u2014puNyazlOkamaJjarI"
  ],
  "tags": [
    "kanchi-aradhana-days"
  ],
  "timing": {
    "angam_number": 17,
    "angam_type": "tithi",
    "jsonClass": "HinduCalendarEventTiming",
    "kaala": "aparaahna",
    "month_number": 10,
    "month_type": "lunar_month",
    "year_start": 4884
  }
}