{
  "description": {
    "en": "He, Soma, initiated with the title Bodhendra by the preceptor Para\u015bivendra adorned the P\u012b\u1e6dha and visiting countries in the palanquin exquisitely decked with gems offered by Bhoja, the king of Dh\u0101r\u0101, inculcating faith in the principles of Advaita in the minds of those who venerated him on the path safeguarded the Ma\u1e6dha from the invaders (mlechas) with the help of the minister of the Kashmiri King Kala\u015ba.  Having stayed in the P\u012b\u1e6dha for thirty-seven years, He reached the Supreme Abode at Aru\u1e47\u0101cala on the New moon day of the month \u0100\u1e63\u0101\u1e0dha in the year \u0102\u015bvara. This preceptor Bodhendra, also known as S\u0101nandr\u0101nanda, was honoured for poetical excellence by Kings\u2014Bhoja, Kala\u015be\u015bvara and others and was intent on travelling through the earth."
  },
  "id": "kAJcI 46 jagadguru zrI~sAndrAnandabOdhEndra sarasvatI ArAdhanA",
  "image": "kanchi-jagadgurus/jagadguru-46.jpg",
  "jsonClass": "HinduCalendarEvent",
  "priority": "puurvaviddha",
  "references_primary": [
    "Punya Shloka Manjari"
  ],
  "references_secondary": [
    "www.kamakoti.org"
  ],
  "shlokas": [
    "bOdhEndrAkhyaH sa sOmO guruparamazivEndrAryavAcA'dhipIThaM\ntiSThan prApyAnyadEzAn pathipathi vinatAn prApayan advayAsthAm.\nzrIdhArAbhOjadattapracuramaNimayAndOlikAklRptayAtraH\nkAzmIrAmAtyapuSyatkaTakasamavanO'dhAnmaThaM mlEcchadUram..89..\nzaradastriMzataM saptApyadhyuSyAnvaruNAcalam(-Sya sa gurOH padam).\njagAma dhAma paramamIzvarASADhaparvaNi..90..\n\u2014puNyazlOkamaJjarI"
  ],
  "tags": [
    "kanchi-aradhana-days"
  ],
  "timing": {
    "angam_number": 30,
    "angam_type": "tithi",
    "jsonClass": "HinduCalendarEventTiming",
    "kaala": "aparahna",
    "month_number": 4,
    "month_type": "lunar_month",
    "year_start": 4199
  }
}